[
    {
        "cca3": "ABW",
        "url": "https://www.arubatoday.com/",
        "timestamp": "2020-09-30",
        "headline": "Springboard to work for the Disabled"
    },
    {
        "cca3": "AFG",
        "url": "https://tolonews.com/",
        "timestamp": "2020-09-30",
        "headline": "'Taliban Shows No Flexibility in Peace': Deputy Minister"
    },
    {
        "cca3": "AGO",
        "url": "https://www.angop.ao/angola/en_us/index.html",
        "timestamp": "2020-09-30",
        "headline": "President urges union to build prosperous Angola"
    },
    {
        "cca3": "AIA",
        "url": "http://theanguillian.com/",
        "timestamp": "2020-09-30",
        "headline": "Ask Your Doctor: ANGINA"
    },
    {
        "cca3": "ALB",
        "url": "https://albaniandailynews.com/",
        "timestamp": "2020-09-30",
        "headline": "\u2018It Is a Hugely Worrying Time\u2019"
    },
    {
        "cca3": "AND",
        "url": "https://all-andorra.com/",
        "timestamp": "2020-09-30",
        "headline": "The International Ski Mountaineering Association Council tries to guarantee a race season 2020-21 as regular as possible"
    },
    {
        "cca3": "ARE",
        "url": "https://www.khaleejtimes.com/",
        "timestamp": "2020-09-30",
        "headline": "Abu Dhabi's Mubadala eyes up to $1b stake in Reliance Retail"
    },
    {
        "cca3": "ARG",
        "url": "https://www.batimes.com.ar/",
        "timestamp": "2020-09-30",
        "headline": "Unedifying spectacle: Trump, Biden stage chaotic first debate"
    },
    {
        "cca3": "ARM",
        "url": "https://armenpress.am/eng/",
        "timestamp": "2020-09-30",
        "headline": "Armenian President informs Egyptian counterpart about war provoked by Azerbaijan"
    },
    {
        "cca3": "ASM",
        "url": "https://samoanews.com/",
        "timestamp": "2020-09-30",
        "headline": "New supervisor welcomed to USCG Marine Safety Detachment"
    },
    {
        "cca3": "ATG",
        "url": "https://antiguaobserver.com/",
        "timestamp": "2020-09-30",
        "headline": "Two cases of dengue confirmed"
    },
    {
        "cca3": "AUS",
        "url": "https://www.smh.com.au/",
        "timestamp": "2020-09-30",
        "headline": "'We make things in Australia': Blueprint to rebuild the nation unveiled"
    },
    {
        "cca3": "AUT",
        "url": "http://www.viennatimes.com/",
        "timestamp": "2020-09-30",
        "headline": "Austria expels Russian diplomat, Moscow responds in kind"
    },
    {
        "cca3": "BDI",
        "url": "https://www.iwacu-burundi.org/englishnews/",
        "timestamp": "2020-09-30",
        "headline": "Economic expert urges government to establish half-year plan for change"
    },
    {
        "cca3": "BEL",
        "url": "https://www.brusselstimes.com/",
        "timestamp": "2020-09-30",
        "headline": "Brussels Airlines will extend its offer to and..."
    },
    {
        "cca3": "BGD",
        "url": "https://www.thehindu.com/",
        "timestamp": "2020-09-30",
        "headline": "Babri Masjid demolition case | Accused did not have a plan, says court"
    },
    {
        "cca3": "BGR",
        "url": "https://sofiaglobe.com/",
        "timestamp": "2020-09-30",
        "headline": "EU Rule of Law report: Bulgaria gets familiar flaws factsheet"
    },
    {
        "cca3": "BHR",
        "url": "https://gulfnews.com/world/gulf/bahrain",
        "timestamp": "2020-09-30",
        "headline": "Bahrain: Man jailed for 7 years for money laundering"
    },
    {
        "cca3": "BHS",
        "url": "https://thenassauguardian.com/",
        "timestamp": "2020-09-30",
        "headline": "Speaker calls for death penalty"
    },
    {
        "cca3": "BIH",
        "url": "https://www.sarajevotimes.com/",
        "timestamp": "2020-09-30",
        "headline": "Prince Albert II of Monaco to Visit Sarajevo"
    },
    {
        "cca3": "BLR",
        "url": "https://eng.belta.by/",
        "timestamp": "2020-09-30",
        "headline": "19:58\n\nMinsk to host electric mobility promotion forum on 16 October\nEconomy"
    },
    {
        "cca3": "BLZ",
        "url": "https://amandala.com.bz/news/",
        "timestamp": "2020-09-30",
        "headline": "The total number of confirmed cases of COVID-19 in Belize now stands at 18"
    },
    {
        "cca3": "BMU",
        "url": "http://www.royalgazette.com/",
        "timestamp": "2020-09-30",
        "headline": "Health food store aims to make up for lost time"
    },
    {
        "cca3": "BRA",
        "url": "https://riotimesonline.com/",
        "timestamp": "2020-09-30",
        "headline": "Rio Legislative Assembly Appoints Deputies to Form Impeachment Court"
    },
    {
        "cca3": "BRB",
        "url": "http://www.loopnewsbarbados.com/",
        "timestamp": "2020-09-30",
        "headline": "Christina Milian gets roasted for eating raw breadfruit on Instagram"
    },
    {
        "cca3": "BRN",
        "url": "https://www.bruneinews.net/",
        "timestamp": "2020-09-30",
        "headline": "Singapore tourist industry unlikely to recover for several years"
    },
    {
        "cca3": "BTN",
        "url": "http://www.bbs.bt/news/",
        "timestamp": "2020-09-30",
        "headline": "Opposition Party writes to the PMO in connection with the CFM closureRead More..."
    },
    {
        "cca3": "BWA",
        "url": "http://www.thepatriot.co.bw/",
        "timestamp": "2020-09-30",
        "headline": "Ngwaketse Council lose P10 million"
    },
    {
        "cca3": "CAN",
        "url": "https://www.cbc.ca/news/canada",
        "timestamp": "2020-09-30",
        "headline": "Why some snowbirds are still heading south this winter despite COVID-19 and a closed land border"
    },
    {
        "cca3": "CHE",
        "url": "https://www.swissinfo.ch/eng/latest-news",
        "timestamp": "2020-09-30",
        "headline": "SWISS airline refunds half a billion francs to passengers"
    },
    {
        "cca3": "CHN",
        "url": "https://www.chinadaily.com.cn/index.html",
        "timestamp": "2020-09-30",
        "headline": "Xi pays tribute to national heroes at Tian'anmen Square"
    },
    {
        "cca3": "CMR",
        "url": "https://www.journalducameroun.com/en/",
        "timestamp": "2020-09-30",
        "headline": "Cameroon: Anglophones still waiting on \u2018Special Status\u2019 one year after Major National Dialogue"
    },
    {
        "cca3": "COK",
        "url": "http://www.cookislandsnews.com/",
        "timestamp": "2020-09-30",
        "headline": "Fibre-optic network construction work carries on"
    },
    {
        "cca3": "COL",
        "url": "https://colombiareports.com/",
        "timestamp": "2020-09-30",
        "headline": "How a US military doctrine became Colombia\u2019s \u2018origin of evil\u2019 | Part 3: Slavery"
    },
    {
        "cca3": "CRI",
        "url": "https://ticotimes.net/",
        "timestamp": "2020-09-30",
        "headline": "Some 34 million jobs lost in Latin America due to pandemic"
    },
    {
        "cca3": "CUB",
        "url": "https://oncubanews.com/en/",
        "timestamp": "2020-09-30",
        "headline": "Cuba adds 66 new COVID-19 cases, the majority from Ciego de \u00c1vila"
    },
    {
        "cca3": "CUW",
        "url": "https://www.curacaochronicle.com/home/",
        "timestamp": "2020-09-30",
        "headline": "Cura\u00e7ao starts registering migrants via food packages"
    },
    {
        "cca3": "CYM",
        "url": "https://www.caymancompass.com/",
        "timestamp": "2020-09-30",
        "headline": "Tourism 2.0: Private jet terminal could bring big spenders"
    },
    {
        "cca3": "CYP",
        "url": "https://cyprus-mail.com/category/cyprus/",
        "timestamp": "2020-09-30",
        "headline": "March held in support of Armenia"
    },
    {
        "cca3": "CZE",
        "url": "http://praguemonitor.com/",
        "timestamp": "2020-09-30",
        "headline": "Pehe: Protest leader's move into politics reflects opposition's lack of threat to Babi\u0161"
    },
    {
        "cca3": "DEU",
        "url": "https://www.zeit.de/english/index",
        "timestamp": "2020-09-30",
        "headline": "Besuchen Sie zeit.de wie gewohnt mit Werbung und Tracking. Details zum Tracking finden Sie in der \n                                Datenschutzerkl\u00e4rung\n                                 und im \n                                Privacy Center."
    },
    {
        "cca3": "DMA",
        "url": "https://dominicanewsonline.com/news/",
        "timestamp": "2020-09-30",
        "headline": "WEATHER (12pm 30th September): Flash Flood Warning is in effect for Dominica until 6:00 PM"
    },
    {
        "cca3": "DNK",
        "url": "http://cphpost.dk/",
        "timestamp": "2020-09-30",
        "headline": "Local Round-Up: Final troll makes stand in Sydhavnen"
    },
    {
        "cca3": "DOM",
        "url": "https://dominicantoday.com/",
        "timestamp": "2020-09-30",
        "headline": "David Collado says the tourism industry \u201cis about to collapse\u201d"
    },
    {
        "cca3": "ECU",
        "url": "https://www.ecuadortimes.net/",
        "timestamp": "2020-09-30",
        "headline": "The 30-S evidenced the manipulation of justice in the time of Corre\u00edsmo"
    },
    {
        "cca3": "EGY",
        "url": "https://www.egypttoday.com/",
        "timestamp": "2020-09-30",
        "headline": "Egypt\u2019s president urges international coordination to face risk of biodiversity decline"
    },
    {
        "cca3": "ERI",
        "url": "https://www.tesfanews.net/",
        "timestamp": "2020-09-30",
        "headline": "Serejeka \u2013 Gindae Asphalt Road Renovated, Expanded"
    },
    {
        "cca3": "ESP",
        "url": "https://english.elpais.com/",
        "timestamp": "2020-09-30",
        "headline": "Madrid, Catalonia reject deal to confine areas with high coronavirus contagion levels"
    },
    {
        "cca3": "EST",
        "url": "https://news.err.ee/",
        "timestamp": "2020-09-30",
        "headline": "Siim Kallas: Loan money does not last forever"
    },
    {
        "cca3": "ETH",
        "url": "https://addisstandard.com/",
        "timestamp": "2020-09-30",
        "headline": "Ethiopia: OFC calls for \u201cgenuine national dialogue\u201d"
    },
    {
        "cca3": "FIN",
        "url": "https://www.helsinkitimes.fi/",
        "timestamp": "2020-09-30",
        "headline": "Covid-19 confirmed cases in Finland and other countries"
    },
    {
        "cca3": "FJI",
        "url": "http://fijitimes.com/",
        "timestamp": "2020-09-30",
        "headline": "Sigatoka fishermen missing after boating tragedy; search in progress"
    },
    {
        "cca3": "FRA",
        "url": "https://www.france24.com/en/france/",
        "timestamp": "2020-09-30",
        "headline": "Five go on trial for seizing 'pillaged' African artwork from Paris museum"
    },
    {
        "cca3": "FRO",
        "url": "http://local.fo/",
        "timestamp": "2020-09-30",
        "headline": "38 active cases: Thetis has established a travel unit to test people all over the country"
    },
    {
        "cca3": "FSM",
        "url": "http://www.kpress.info/",
        "timestamp": "2020-09-30",
        "headline": "President amends decree on commercial fishing vessels to prevent  COVID-19 risk"
    },
    {
        "cca3": "GBR",
        "url": "https://www.thetimes.co.uk/",
        "timestamp": "2020-09-30",
        "headline": "Virus \u2018could be contained in north\u2019"
    },
    {
        "cca3": "GEO",
        "url": "http://georgiatoday.ge/",
        "timestamp": "2020-09-30",
        "headline": "Tourism Revived amid Pandemic"
    },
    {
        "cca3": "GGY",
        "url": "https://guernseypress.com/",
        "timestamp": "2020-09-30",
        "headline": "Law change now in force to allow UK-prescribed medical cannabis"
    },
    {
        "cca3": "GHA",
        "url": "https://www.ghanaweb.com/",
        "timestamp": "2020-09-30",
        "headline": "Okada riders swarm Bawumia as he embarks on Accra tour"
    },
    {
        "cca3": "GIB",
        "url": "https://www.chronicle.gi/",
        "timestamp": "2020-09-30",
        "headline": "Positive Covid-19 case at St Paul\u2019s Lower Primary School"
    },
    {
        "cca3": "GMB",
        "url": "https://standard.gm/",
        "timestamp": "2020-09-30",
        "headline": "GDC warns Barrow to beware of deceptors, denies cross-carpeting claims"
    },
    {
        "cca3": "GNQ",
        "url": "https://www.guineaecuatorialpress.com/?lang=en",
        "timestamp": "2020-09-30",
        "headline": "President takes part in Top Level Event on Financing of Development in era of COVID-19"
    },
    {
        "cca3": "GRC",
        "url": "https://www.ekathimerini.com/",
        "timestamp": "2020-09-30",
        "headline": "Parthenon illuminated in full splendor"
    },
    {
        "cca3": "GRD",
        "url": "https://www.thegrenadainformer.com/",
        "timestamp": "2020-09-30",
        "headline": "\"Dr Andrew\" heads back to\u2026"
    },
    {
        "cca3": "GUM",
        "url": "https://www.postguam.com/news/local/",
        "timestamp": "2020-09-30",
        "headline": "Extra $300 or $400 in weekly unemployment aid payout still awaits FEMA guidance"
    },
    {
        "cca3": "GUY",
        "url": "https://www.stabroeknews.com/news/guyana/",
        "timestamp": "2020-09-30",
        "headline": "Airports could be open to commercial flights after Oct 15"
    },
    {
        "cca3": "HKG",
        "url": "https://www.scmp.com/",
        "timestamp": "2020-09-30",
        "headline": "\u2018Is this American-style civilisation?\u2019 Trump vs Biden shocks Chinese viewers"
    },
    {
        "cca3": "HND",
        "url": "http://www.hondurasnews.com/",
        "timestamp": "2020-09-30",
        "headline": "Official list of the 23 players representing Honduras in the 2019 Gold Cup \u2013 Honduras National Team Soccer"
    },
    {
        "cca3": "HRV",
        "url": "https://www.thedubrovniktimes.com/news/croatia",
        "timestamp": "2020-09-30",
        "headline": "President of the Croatian Parliament goes into self-isolation for 14 days"
    },
    {
        "cca3": "HTI",
        "url": "https://www.haitilibre.com/en/",
        "timestamp": "2020-09-30",
        "headline": "iciHaiti - DR : 88 illegal Haitian migrants repatriated"
    },
    {
        "cca3": "HUN",
        "url": "https://dailynewshungary.com/",
        "timestamp": "2020-09-30",
        "headline": "Liget Budapest \u2013 City assembly approves amendment to construction rules"
    },
    {
        "cca3": "IDN",
        "url": "https://en.antaranews.com/",
        "timestamp": "2020-09-30",
        "headline": "Minister urges 8 governors to use hotels as quarantine facilities"
    },
    {
        "cca3": "IND",
        "url": "https://www.thehindu.com/",
        "timestamp": "2020-09-30",
        "headline": "Babri Masjid demolition case | Accused did not have a plan, says court"
    },
    {
        "cca3": "IRL",
        "url": "https://www.irishtimes.com/",
        "timestamp": "2020-09-30",
        "headline": "Joe Biden is dodging the culture war to focus on class \u2013 and he\u2019s right"
    },
    {
        "cca3": "IRN",
        "url": "https://irannewsdaily.com/",
        "timestamp": "2020-09-30",
        "headline": "No Power Can Harm Iran\u2019s Exports, Imports: NITC official"
    },
    {
        "cca3": "IRQ",
        "url": "https://www.iraqinews.com/",
        "timestamp": "2020-09-30",
        "headline": "Iraq declares three-day mourning period after deadly protests"
    },
    {
        "cca3": "ISL",
        "url": "https://icelandmonitor.mbl.is/news/latest/",
        "timestamp": "2020-09-30",
        "headline": "Predicting 20-40 New Cases of COVID-19 a Day"
    },
    {
        "cca3": "ISR",
        "url": "https://www.haaretz.com/",
        "timestamp": "2020-09-30",
        "headline": "COVID-19 Netanyahu: Lockdown Exit Strategy Could Take Up to a Year"
    },
    {
        "cca3": "ITA",
        "url": "https://www.ansa.it/english/",
        "timestamp": "2020-09-30",
        "headline": "Two M5S Senators test positive for COVID-19"
    },
    {
        "cca3": "JAM",
        "url": "http://jamaica-gleaner.com/",
        "timestamp": "2020-09-30",
        "headline": "Gov\u2019t to assist with funeral expenses of 8-y-old St Catherine girl"
    },
    {
        "cca3": "JEY",
        "url": "https://www.bailiwickexpress.com/jsy/news/",
        "timestamp": "2020-09-30",
        "headline": "Serial offender jailed for stamping on man's head\t\t\t\t\t\t\t\t\t\t\t\t\tWednesday 30 September 2020"
    },
    {
        "cca3": "JOR",
        "url": "https://www.jordantimes.com/",
        "timestamp": "2020-09-30",
        "headline": "King mourns passing of Emir Sheikh Sabah"
    },
    {
        "cca3": "JPN",
        "url": "https://mainichi.jp/english/",
        "timestamp": "2020-09-30",
        "headline": "Boy successfully masqueraded as Tokyo elite high school student for months"
    },
    {
        "cca3": "KAZ",
        "url": "https://astanatimes.com/",
        "timestamp": "2020-09-30",
        "headline": "Kazakhstan Renders Humanitarian Aid to Provinces Hit By Flooding in Afghanistan"
    },
    {
        "cca3": "KEN",
        "url": "https://www.nation.co.ke/",
        "timestamp": "2020-09-30",
        "headline": "AG wants Mama Ngina waterfront suit dismissed"
    },
    {
        "cca3": "KGZ",
        "url": "http://en.kabar.kg/",
        "timestamp": "2020-09-30",
        "headline": "Kyrgyz president to deliver video message at Biodiversity Summit"
    },
    {
        "cca3": "KHM",
        "url": "https://www.phnompenhpost.com/",
        "timestamp": "2020-09-30",
        "headline": "PM: Reset of 2030 SDGs warranted"
    },
    {
        "cca3": "KIR",
        "url": "https://kiribatiupdates.com.ki/",
        "timestamp": "2020-09-30",
        "headline": "Kiribati national election begins today."
    },
    {
        "cca3": "KNA",
        "url": "https://www.thestkittsnevisobserver.com/",
        "timestamp": "2020-09-30",
        "headline": "Changes made in Nevis Ministry of Communications and Works"
    },
    {
        "cca3": "KOR",
        "url": "http://english.chosun.com/",
        "timestamp": "2020-09-30",
        "headline": "U.S. Wants Korea to Join Anti-China Economic Bloc"
    },
    {
        "cca3": "LAO",
        "url": "https://laotiantimes.com/",
        "timestamp": "2020-09-30",
        "headline": "Hundreds of Foreigners Remain Stranded in Laos"
    },
    {
        "cca3": "LBN",
        "url": "http://www.naharnet.com/",
        "timestamp": "2020-09-30",
        "headline": "Democrat challenger Joe Biden on Wednesday branded Donald Trump's debate performance a \"national embarrassment\" for not addressing concerns of ..."
    },
    {
        "cca3": "LBR",
        "url": "https://www.liberianobserver.com/",
        "timestamp": "2020-09-30",
        "headline": "Suspected Arson at St. Matthew Lutheran High School"
    },
    {
        "cca3": "LBY",
        "url": "https://www.libyaobserver.ly/",
        "timestamp": "2020-09-30",
        "headline": "UNSMIL says security, military talks in Hurghada have ended"
    },
    {
        "cca3": "LCA",
        "url": "https://www.thevoiceslu.com/",
        "timestamp": "2020-09-30",
        "headline": "Man Arrested In Scheme to Sell Guns In Saint Lucia"
    },
    {
        "cca3": "LIE",
        "url": "https://www.liechtenstein.li/en/liechtenstein-news/",
        "timestamp": "2020-09-30",
        "headline": "Did you know that..."
    },
    {
        "cca3": "LKA",
        "url": "http://www.dailymirror.lk/",
        "timestamp": "2020-09-30",
        "headline": "Leaving us in tears..."
    },
    {
        "cca3": "LSO",
        "url": "http://lestimes.com/",
        "timestamp": "2020-09-30",
        "headline": "Law indexing critical for economic reforms- Mokuku"
    },
    {
        "cca3": "LTU",
        "url": "https://en.delfi.lt/",
        "timestamp": "2020-09-30",
        "headline": "Naus\u0117da: Macron\u2019s visit helped improve mutual understanding"
    },
    {
        "cca3": "LUX",
        "url": "https://luxtimes.lu/",
        "timestamp": "2020-09-30",
        "headline": "Luxembourg yearns for government to step into property market"
    },
    {
        "cca3": "LVA",
        "url": "https://eng.lsm.lv/",
        "timestamp": "2020-09-30",
        "headline": "In Riga overcast\n+14 \u00b0C, ENE wind, 2,60m/s"
    },
    {
        "cca3": "MAC",
        "url": "https://macaudailytimes.com.mo/",
        "timestamp": "2020-09-30",
        "headline": "HKSAR mulls reopening borders to Macau, mainland"
    },
    {
        "cca3": "MAF",
        "url": "https://www.thedailyherald.sx/",
        "timestamp": "2020-09-30",
        "headline": "First two businesses get financial aid via Enterprise Support Project"
    },
    {
        "cca3": "MAR",
        "url": "https://www.moroccoworldnews.com/",
        "timestamp": "2020-09-30",
        "headline": "Chariot Oil & Gas: Northern Morocco\u2019s Energy Resources Exceed 1 Trillion Cubic Feet"
    },
    {
        "cca3": "MCO",
        "url": "https://www.monaco-tribune.com/en/",
        "timestamp": "2020-09-30",
        "headline": "Bob Carlton, Jacquemus, Fragonard\u2026 fashion brands inspired by the French Riviera"
    },
    {
        "cca3": "MDA",
        "url": "https://www.moldpres.md/en/",
        "timestamp": "2020-09-30",
        "headline": "Moldovan PM visits Comrat city affected by floods"
    },
    {
        "cca3": "MDV",
        "url": "https://en.sun.mv/",
        "timestamp": "2020-09-30",
        "headline": "School hours in virus-free islands to be increased to 5"
    },
    {
        "cca3": "MEX",
        "url": "https://mexiconewsdaily.com/",
        "timestamp": "2020-09-30",
        "headline": "Mathematician warns of coronavirus flare-up as positivity rate stops declining"
    },
    {
        "cca3": "MHL",
        "url": "https://marshallislandsjournal.com/",
        "timestamp": "2020-09-30",
        "headline": "Covid checks happily received"
    },
    {
        "cca3": "MLT",
        "url": "https://www.maltatoday.com.mt/",
        "timestamp": "2020-09-30",
        "headline": "[WATCH] Lampuki wars: Gozo fishers catch Tunisian poachers on video"
    },
    {
        "cca3": "MMR",
        "url": "https://www.mmtimes.com/",
        "timestamp": "2020-09-30",
        "headline": "Myanmar officials to get controversial car permits ahead of polls"
    },
    {
        "cca3": "MNG",
        "url": "https://montsame.mn/en/",
        "timestamp": "2020-09-30",
        "headline": "Photos tell a history"
    },
    {
        "cca3": "MWI",
        "url": "https://www.nyasatimes.com/",
        "timestamp": "2020-09-30",
        "headline": "President Chakwera jets in Zimbabwe to bolster ties"
    },
    {
        "cca3": "MYS",
        "url": "https://www.nst.com.my/",
        "timestamp": "2020-09-30",
        "headline": "Opinion\n\n\nColumnists\n\n\nLetters\n\n\nLeader"
    },
    {
        "cca3": "NAM",
        "url": "https://www.namibian.com.na/",
        "timestamp": "2020-09-30",
        "headline": "South African coach Mosimane quits Sundowns, linked to Ahly"
    },
    {
        "cca3": "NGA",
        "url": "https://www.vanguardngr.com/",
        "timestamp": "2020-09-30",
        "headline": "BREAKING: Presidency reverses self, says to make morning broadcast 7am October 1"
    },
    {
        "cca3": "NLD",
        "url": "https://www.dutchnews.nl/",
        "timestamp": "2020-09-30",
        "headline": "Dutch 'urgently advised' to wear face masks in shops, cafes and public buildings"
    },
    {
        "cca3": "NOR",
        "url": "https://www.tnp.no/",
        "timestamp": "2020-09-30",
        "headline": "The Fire on Melk\u00f8ya is One of the Most Serious Incidents in Norway\u00b4s Oil History"
    },
    {
        "cca3": "NPL",
        "url": "https://thehimalayantimes.com/",
        "timestamp": "2020-09-30",
        "headline": "1,559 new cases take Nepal\u2019s coronavirus tally to 77,817 on Wednesday"
    },
    {
        "cca3": "NRU",
        "url": "http://nauru-news.com/",
        "timestamp": "2020-09-30",
        "headline": "USP special council meeting resolves to terminate proceedings against VCP"
    },
    {
        "cca3": "NZL",
        "url": "https://www.nzherald.co.nz/",
        "timestamp": "2020-09-30",
        "headline": "World reacts to 'chaotic' Trump / Biden debate"
    },
    {
        "cca3": "OMN",
        "url": "https://timesofoman.com/",
        "timestamp": "2020-09-30",
        "headline": "Oman\u2019s Foreign Minister Sayyid Badr addresses 75th session of UN General Assembly"
    },
    {
        "cca3": "PAK",
        "url": "https://www.dawn.com/",
        "timestamp": "2020-09-30",
        "headline": "Joe Biden's use of 'Inshallah' to mock Trump raises eyebrows"
    },
    {
        "cca3": "PAN",
        "url": "https://www.panamatoday.com/",
        "timestamp": "2020-09-30",
        "headline": "The elected president of Panama, Laurentino Cortizo, said that \"the country needs peace\""
    },
    {
        "cca3": "PER",
        "url": "https://www.peruviantimes.com/",
        "timestamp": "2020-09-30",
        "headline": "Spain approves extradition of Justice Hinostroza, for crimes within Peru\u2019s court system"
    },
    {
        "cca3": "PHL",
        "url": "https://www.inquirer.net/",
        "timestamp": "2020-09-30",
        "headline": "Celebrating birthday as House Speaker part of term-sharing deal \u2013 Cayetano"
    },
    {
        "cca3": "PLW",
        "url": "https://www.palaugov.pw/news/",
        "timestamp": "2020-09-30",
        "headline": "Palau Pledge honored with D&AD\u2019s Black Pencil accolade of the decade"
    },
    {
        "cca3": "PNG",
        "url": "https://postcourier.com.pg/",
        "timestamp": "2020-09-30",
        "headline": "Foreigner engaged in sham marriages with local women caught"
    },
    {
        "cca3": "POL",
        "url": "https://www.polskieradio.pl/395",
        "timestamp": "2020-09-30",
        "headline": "UPDATE 2: Polish PM unveils new Cabinet after deal to defuse coalition crisis"
    },
    {
        "cca3": "PRT",
        "url": "https://www.theportugalnews.com/",
        "timestamp": "2020-09-30",
        "headline": "Portuguese students showing \u201csignificant improvement against all odds"
    },
    {
        "cca3": "PSE",
        "url": "http://english.pnn.ps/",
        "timestamp": "2020-09-30",
        "headline": "Bethlehem: Tourism employees raise sounds of protest to seek support"
    },
    {
        "cca3": "QAT",
        "url": "https://thepeninsulaqatar.com/",
        "timestamp": "2020-09-30",
        "headline": "Oil giant Shell axes thousands of jobs on virus fallout"
    },
    {
        "cca3": "ROU",
        "url": "https://www.romaniajournal.ro/",
        "timestamp": "2020-09-30",
        "headline": "Record high of COVID infections as Romania exceeds 2,000 daily cases"
    },
    {
        "cca3": "RUS",
        "url": "https://www.themoscowtimes.com/",
        "timestamp": "2020-09-30",
        "headline": "\u2018We\u2019re Out of Beds\u2019: Russia\u2019s Resurgent Coronavirus Outbreak Is Approaching First Peak"
    },
    {
        "cca3": "RWA",
        "url": "https://www.newtimes.co.rw/",
        "timestamp": "2020-09-30",
        "headline": "Genocide: French court upholds decision to send Kabuga to stand trial in \nArusha"
    },
    {
        "cca3": "SAU",
        "url": "https://saudigazette.com.sa/",
        "timestamp": "2020-09-30",
        "headline": "Bahrain, UAE hold funeral prayer\rin absentia for late Kuwait\u00e2\u0080\u0099s emir"
    },
    {
        "cca3": "SDN",
        "url": "https://www.sudantribune.com/",
        "timestamp": "2020-09-30",
        "headline": "Three Sudanese political groups call to normalize with Israel"
    },
    {
        "cca3": "SGP",
        "url": "https://www.straitstimes.com/global",
        "timestamp": "2020-09-30",
        "headline": "A million lives lost.\r\nA million stories of tragedy."
    },
    {
        "cca3": "SLB",
        "url": "https://www.solomontimes.com/",
        "timestamp": "2020-09-30",
        "headline": "Wale Welcomes Students\u2019 Home: \u201cLet\u2019s Continue Praying for the Country\u201d"
    },
    {
        "cca3": "SLE",
        "url": "https://www.thesierraleonetelegraph.com/",
        "timestamp": "2020-09-30",
        "headline": "Sierra Leonean blues and jazz singer and guitarist \u2013 Bai Kamara nominated in US Blues Blast Music Award"
    },
    {
        "cca3": "SRB",
        "url": "https://www.b92.net/eng/",
        "timestamp": "2020-09-30",
        "headline": "72 newly infected, no deaths"
    },
    {
        "cca3": "SVK",
        "url": "https://spectator.sme.sk/",
        "timestamp": "2020-09-30",
        "headline": "Government looks to crack down on crooks\u2019 property and judicial corruption"
    },
    {
        "cca3": "SVN",
        "url": "http://www.sloveniatimes.com/",
        "timestamp": "2020-09-30",
        "headline": "Slovenia and Portugal talk about shared 2021 EU presidency"
    },
    {
        "cca3": "SWE",
        "url": "https://www.thelocal.se/",
        "timestamp": "2020-09-30",
        "headline": "Learn about Project Shield"
    },
    {
        "cca3": "SWZ",
        "url": "http://www.times.co.sz/",
        "timestamp": "2020-09-30",
        "headline": "POOR WILL SUFFER FROM PRICE GOUGING"
    },
    {
        "cca3": "THA",
        "url": "https://www.bangkokpost.com/",
        "timestamp": "2020-09-30",
        "headline": "Graft ranking needs rethink"
    },
    {
        "cca3": "TJK",
        "url": "https://asiaplustj.info/en",
        "timestamp": "2020-09-30",
        "headline": "Who is he - a Tajik who was included in the UK sanctions list along with Lukashenko?"
    },
    {
        "cca3": "TKM",
        "url": "https://en.turkmen.news/",
        "timestamp": "2020-09-30",
        "headline": "Ashgabat Women Exasperated at Tacit Ban on Driving"
    },
    {
        "cca3": "TUR",
        "url": "https://www.hurriyetdailynews.com/",
        "timestamp": "2020-09-30",
        "headline": "Turkey calls on EU to be impartial on Med row, boost dialogue"
    },
    {
        "cca3": "TWN",
        "url": "https://www.taipeitimes.com/",
        "timestamp": "2020-09-30",
        "headline": "Minister touts Taiwan-US collaboration"
    },
    {
        "cca3": "TZA",
        "url": "https://www.thecitizen.co.tz/",
        "timestamp": "2020-09-30",
        "headline": "Seif lays down case for Zanzibar full autonomy"
    },
    {
        "cca3": "UGA",
        "url": "https://www.monitor.co.ug/",
        "timestamp": "2020-09-30",
        "headline": "World's first person to be cured of HIV dies"
    },
    {
        "cca3": "UKR",
        "url": "https://www.kyivpost.com/",
        "timestamp": "2020-09-30",
        "headline": "Dynamo Kyiv wins Belgian Gent, advances to Champions League group stage"
    },
    {
        "cca3": "USA",
        "url": "https://www.wsj.com/",
        "timestamp": "2020-09-30",
        "headline": "House Democrats to Call for Big Tech Breakups"
    },
    {
        "cca3": "UZB",
        "url": "https://kun.uz/en",
        "timestamp": "2020-09-30",
        "headline": "Uzbekistan\u2019s international reserves as of September 1 announced"
    },
    {
        "cca3": "VAT",
        "url": "https://www.vaticannews.va/en.html",
        "timestamp": "2020-09-30",
        "headline": "New Apostolic Letter highlights St Jerome\u2019s love of Scripture"
    },
    {
        "cca3": "VNM",
        "url": "https://vietnamnews.vn/",
        "timestamp": "2020-09-30",
        "headline": "Construction starts on North-South Expressway component projects"
    },
    {
        "cca3": "ZAF",
        "url": "https://www.timeslive.co.za/",
        "timestamp": "2020-09-30",
        "headline": "Uni's to open, international students quarantine, matric results in Feb: ..."
    },
    {
        "cca3": "ZMB",
        "url": "https://www.lusakatimes.com/",
        "timestamp": "2020-09-30",
        "headline": "High Court judge  dismisses a case in which Pilato and  others wanted to challenge the Voter Registration Process"
    },
    {
        "cca3": "ZWE",
        "url": "https://www.newzimbabwe.com/",
        "timestamp": "2020-09-30",
        "headline": "Schools without water cannot re-open \u2013 govt"
    }
]